filesanitize.py
filesanitize-1.1.0.dist-info/METADATA
filesanitize-1.1.0.dist-info/RECORD
filesanitize-1.1.0.dist-info/WHEEL
filesanitize-1.1.0.dist-info/top_level.txt
filesanitize-1.1.0.dist-info/zip-safe
