Metadata-Version: 2.1
Name: filesanitize
Version: 1.1.0
Summary: Filesanitize is a small library for making save paths and filenames by removing accents and special chars
Home-page: https://gitlab.com/marcinjn/filesanitize
Author: Marcin Nowak
Author-email: marcin.j.nowak@gmail.com
License: BSD
Platform: any
Classifier: Development Status :: 5 - Production/Stable
Classifier: Environment :: MacOS X
Classifier: Environment :: Other Environment
Classifier: Intended Audience :: Developers
Classifier: License :: OSI Approved :: BSD License
Classifier: Programming Language :: Python
Classifier: Programming Language :: Python :: 2
Classifier: Programming Language :: Python :: 2.6
Classifier: Programming Language :: Python :: 2.7
Classifier: Programming Language :: Python :: 3
Classifier: Programming Language :: Python :: 3.6
Classifier: Programming Language :: Python :: Implementation :: PyPy
Classifier: Topic :: Software Development
Classifier: Topic :: System
Classifier: Topic :: Utilities
Requires-Dist: translitcodec (==0.4)
Requires-Dist: six
